graphql/__init__.py
graphql/graphql.py
graphql/py.typed
graphql/version.py
graphql/error/__init__.py
graphql/error/format_error.py
graphql/error/graphql_error.py
graphql/error/invalid.py
graphql/error/located_error.py
graphql/error/syntax_error.py
graphql/execution/__init__.py
graphql/execution/execute.py
graphql/execution/middleware.py
graphql/execution/values.py
graphql/language/__init__.py
graphql/language/ast.py
graphql/language/block_string.py
graphql/language/directive_locations.py
graphql/language/lexer.py
graphql/language/location.py
graphql/language/parser.py
graphql/language/predicates.py
graphql/language/print_location.py
graphql/language/printer.py
graphql/language/source.py
graphql/language/token_kind.py
graphql/language/visitor.py
graphql/pyutils/__init__.py
graphql/pyutils/awaitable_or_value.py
graphql/pyutils/cached_property.py
graphql/pyutils/convert_case.py
graphql/pyutils/dedent.py
graphql/pyutils/did_you_mean.py
graphql/pyutils/event_emitter.py
graphql/pyutils/frozen_dict.py
graphql/pyutils/frozen_error.py
graphql/pyutils/frozen_list.py
graphql/pyutils/identity_func.py
graphql/pyutils/inspect.py
graphql/pyutils/is_finite.py
graphql/pyutils/is_integer.py
graphql/pyutils/is_invalid.py
graphql/pyutils/is_nullish.py
graphql/pyutils/suggestion_list.py
graphql/subscription/__init__.py
graphql/subscription/map_async_iterator.py
graphql/subscription/subscribe.py
graphql/type/__init__.py
graphql/type/definition.py
graphql/type/directives.py
graphql/type/introspection.py
graphql/type/scalars.py
graphql/type/schema.py
graphql/type/validate.py
graphql/utilities/__init__.py
graphql/utilities/assert_valid_name.py
graphql/utilities/ast_from_value.py
graphql/utilities/build_ast_schema.py
graphql/utilities/build_client_schema.py
graphql/utilities/coerce_value.py
graphql/utilities/concat_ast.py
graphql/utilities/extend_schema.py
graphql/utilities/find_breaking_changes.py
graphql/utilities/find_deprecated_usages.py
graphql/utilities/get_operation_ast.py
GraphQL_core_next-1.1.1.dist-info/LICENSE
GraphQL_core_next-1.1.1.dist-info/METADATA
GraphQL_core_next-1.1.1.dist-info/WHEEL
GraphQL_core_next-1.1.1.dist-info/top_level.txt
GraphQL_core_next-1.1.1.dist-info/RECORD
