Metadata-Version: 2.1
Name: GraphQL-core-next
Version: 1.1.1
Summary: GraphQL-core-next is a Python port of GraphQL.js, the JavaScript reference implementation for GraphQL.
Home-page: https://github.com/graphql-python/graphql-core-next
Author: Christoph Zwerschke
Author-email: cito@online.de
License: MIT license
Keywords: graphql
Platform: UNKNOWN
Classifier: Development Status :: 5 - Production/Stable
Classifier: Intended Audience :: Developers
Classifier: Topic :: Software Development :: Libraries
Classifier: License :: OSI Approved :: MIT License
Classifier: Programming Language :: Python :: 3
Classifier: Programming Language :: Python :: 3.6
Classifier: Programming Language :: Python :: 3.7
Requires-Python: >=3.6,<4
